dyneusr/__init__.py
dyneusr/_version.py
dyneusr/core.py
dyneusr/datasets/__init__.py
dyneusr/datasets/trefoil.py
dyneusr/mapper/__init__.py
dyneusr/mapper/utils.py
dyneusr/mapper/wrappers.py
dyneusr/tools/__init__.py
dyneusr/tools/graph_utils.py
dyneusr/tools/mixture.py
dyneusr/tools/networkx_utils.py
dyneusr/visuals/__init__.py
dyneusr/visuals/annotation.py
dyneusr/visuals/plotting.py
dyneusr/visuals/visualize.py
dyneusr/visuals/templates/index-2D.html
dyneusr/visuals/templates/index-3D.html
dyneusr/visuals/templates/index-4D.html
dyneusr/visuals/templates/index-save-svg.html
dyneusr/visuals/templates/index.html
dyneusr-0.3.11.dist-info/LICENSE
dyneusr-0.3.11.dist-info/METADATA
dyneusr-0.3.11.dist-info/WHEEL
dyneusr-0.3.11.dist-info/top_level.txt
dyneusr-0.3.11.dist-info/RECORD
