Metadata-Version: 2.1
Name: dyneusr
Version: 0.3.11
Summary: Dynamical Neural Spatiotemporal Representations.
Home-page: https://braindynamicslab.github.io/dyneusr
Author: Caleb Geniesse
Author-email: geniesse@stanford.edu
License: BSD-3
Keywords: brain dynamics,topology data analysis,neuroimaging,brain networks,mapper,visualization
Platform: UNKNOWN
Classifier: Intended Audience :: Science/Research
Classifier: Topic :: Scientific/Engineering :: Information Analysis
Classifier: Topic :: Scientific/Engineering :: Visualization
Classifier: License :: OSI Approved :: BSD License
Classifier: Operating System :: OS Independent
Classifier: Programming Language :: Python :: 3
Classifier: Programming Language :: Python :: 3.6
Classifier: Programming Language :: Python :: 3.7
Requires-Python: >=3.6
Requires-Dist: setuptools
Requires-Dist: pytest
Requires-Dist: ipython
Requires-Dist: numpy (>=1.16)
Requires-Dist: pandas
Requires-Dist: scipy
Requires-Dist: scikit-learn
Requires-Dist: matplotlib
Requires-Dist: seaborn
Requires-Dist: networkx
Requires-Dist: nilearn
Requires-Dist: kmapper (==1.2.0)
Requires-Dist: joblib
